{"id":"1604959608294-3ac25ffc5d250adf","schemaSHA512":"309450804bbf9362ed0182eb1ff10f57808eb3a4340397dcb4d996fcf014b75f8ba683223dc16acb20c16e86eb76cf62a6997e423b6a20ab36f0278e051d49b3","name":"My First Hive","description":"","slug":"my-first-hive","topics":[],"honeycombs":[{"id":"1604959608318-4cdcb7a60a5e7249","name":"Drafts","slug":"drafts","isDraft":true},{"id":"1604959608318-67f367f7002ffacb","name":"Published","slug":"published","isDraft":false}],"connections":[{"packageName":"@humm/reader","packageLocation":"/Users/David/Projects/humm-reader","connectionType":"capability","capabilityType":"website-generator","title":"humm Reader","description":"A website generator for the humm Publisher","dependencies":[],"settingsDependencies":[],"settings":{}}],"createdAt":"2020-11-09T22:06:48.318Z","updatedAt":"2020-11-10T05:39:23.917Z","hiveKeyPair":{"public":"bDmdnBHLXS9rMtMKAHr3rYu+Q/RK1SKCjmmNdYAZ33I=","secret":"ci/sL76qhGaxMIAvfzb2sMBNs3zu0nsPY7TJ6DQp8xg="}}