{"id":"1604959608294-3ac25ffc5d250adf","schemaSHA512":"309450804bbf9362ed0182eb1ff10f57808eb3a4340397dcb4d996fcf014b75f8ba683223dc16acb20c16e86eb76cf62a6997e423b6a20ab36f0278e051d49b3","name":"My First Hive","description":"","slug":"my-first-hive","topics":[],"honeycombs":[{"id":"1604959608318-4cdcb7a60a5e7249","name":"Drafts","slug":"drafts","isDraft":true},{"id":"1604959608318-67f367f7002ffacb","name":"Published","slug":"published","isDraft":false}],"connections":[{"connectionType":"service","title":"Humm Publisher","description":"A template for building a humm connection","packageName":"@hummhive/publisher","packageLocation":"@hummhive/publisher","dependencies":[],"settingsDependencies":[],"settings":{},"version":"1.0.3","apiVersion":"0.1.0"},{"connectionType":"service","title":"Humm AWS Core","description":"Enables your hive to use AWS","packageName":"@hummhive/aws-core","packageLocation":"/Users/David/Projects/humm-aws-core","dependencies":[],"settingsDependencies":[],"settings":{},"version":"1.0.1","apiVersion":"0.1.0"},{"connectionType":"capability","capabilityType":"website-generator","title":"humm Reader","description":"A website generator for the humm Publisher","packageName":"@hummhive/reader","packageLocation":"/Users/David/Projects/humm-reader","dependencies":[],"settingsDependencies":[],"settings":{},"version":"1.0.0","apiVersion":"0.1.0"}],"hiveKeyPair":{"public":"bDmdnBHLXS9rMtMKAHr3rYu+Q/RK1SKCjmmNdYAZ33I=","secret":"ci/sL76qhGaxMIAvfzb2sMBNs3zu0nsPY7TJ6DQp8xg="},"createdAt":"2020-11-09T22:06:48.318Z","updatedAt":"2020-12-05T07:34:41.369Z"}